pip_pasm/__init__.py
pip_pasm/helper.py
pip_pasm/network_model.py
pip_pasm/pip_pasm.py
pip_pasm/setup.py
pasm-0.0.3.dist-info/LICENSE
pasm-0.0.3.dist-info/METADATA
pasm-0.0.3.dist-info/WHEEL
pasm-0.0.3.dist-info/top_level.txt
pasm-0.0.3.dist-info/RECORD
